idcheckio/utils.py
idcheckio/__init__.py
idcheckio-0.0.4.dist-info/pbr.json
idcheckio-0.0.4.dist-info/top_level.txt
idcheckio-0.0.4.dist-info/METADATA
idcheckio-0.0.4.dist-info/DESCRIPTION.rst
idcheckio-0.0.4.dist-info/metadata.json
idcheckio-0.0.4.dist-info/WHEEL
idcheckio-0.0.4.dist-info/RECORD
